fedex_generator/__init__.py
fedex_generator/Measures/BaseMeasure.py
fedex_generator/Measures/Bins.py
fedex_generator/Measures/DiversityMeasure.py
fedex_generator/Measures/ExceptionalityMeasure.py
fedex_generator/Measures/NormalizedDiversityMeasure.py
fedex_generator/Measures/ShapleyMeasure.py
fedex_generator/Measures/__init__.py
fedex_generator/Operations/BJoin.py
fedex_generator/Operations/Filter.py
fedex_generator/Operations/GroupBy.py
fedex_generator/Operations/Join.py
fedex_generator/Operations/Operation.py
fedex_generator/Operations/__init__.py
fedex_generator/commons/DatasetRelation.py
fedex_generator/commons/__init__.py
fedex_generator/commons/consts.py
fedex_generator/commons/kstest.py
fedex_generator/commons/utils.py
fedex_generator-1.0.6.0.dist-info/licenses/LICENSE
fedex_generator-1.0.6.0.dist-info/licenses/NOTICE
fedex_generator-1.0.6.0.dist-info/METADATA
fedex_generator-1.0.6.0.dist-info/WHEEL
fedex_generator-1.0.6.0.dist-info/top_level.txt
fedex_generator-1.0.6.0.dist-info/RECORD
