Metadata-Version: 2.4
Name: fedex_generator
Version: 1.0.6.0
Project-URL: Git, https://github.com/analysis-bots/FEDEx_Generator
License-File: LICENSE
License-File: NOTICE
Requires-Dist: wheel
Requires-Dist: pandas>=2.2.3
Requires-Dist: numpy>=2.1.3
Requires-Dist: matplotlib>=3.9.0
Requires-Dist: scipy>=1.14.1
Requires-Dist: paretoset>=1.2.4
Dynamic: description
Dynamic: description-content-type
Dynamic: license-file
Dynamic: project-url
Dynamic: requires-dist
